emeis/__init__.py
emeis/conftest.py
emeis/emeis_metadata.py
emeis/settings.py
emeis/urls.py
emeis/wsgi.py
emeis/core/__init__.py
emeis/core/apps.py
emeis/core/factories.py
emeis/core/filters.py
emeis/core/models.py
emeis/core/serializers.py
emeis/core/urls.py
emeis/core/utils.py
emeis/core/views.py
emeis/core/visibilities.py
emeis/core/management/__init__.py
emeis/core/management/commands/__init__.py
emeis/core/management/commands/create_scope.py
emeis/core/migrations/0001_initial.py
emeis/core/migrations/0002_data_bootstrap.py
emeis/core/migrations/0003_localized_city.py
emeis/core/migrations/0004_use_abstract_base_user.py
emeis/core/migrations/0005_manager_on_user_model.py
emeis/core/migrations/0006_rename_field_meta_metainfo.py
emeis/core/migrations/0007_change_JSONField_to_native_django_model_field.py
emeis/core/migrations/0008_scope_is_active.py
emeis/core/migrations/0009_alter_scope_parent.py
emeis/core/migrations/0010_scope_full_name.py
emeis/core/migrations/0011_mptt_to_tree_queries.py
emeis/core/migrations/0012_parents_as_arrayfield.py
emeis/core/migrations/__init__.py
emeis/core/templates/user_list.xlsx
emeis/core/tests/__init__.py
emeis/core/tests/test_api.py
emeis/core/tests/test_create_scope_command.py
emeis/core/tests/test_filters.py
emeis/core/tests/test_models.py
emeis/core/tests/test_permissions.py
emeis/core/tests/test_prefetch_visibility.py
emeis/core/tests/test_views.py
emeis/core/tests/test_visibility.py
emeis/core/tests/snapshots/__init__.py
emeis/core/tests/snapshots/snap_test_api.py
emeis/core/tests/snapshots/snap_test_views.py
emeis/oidc_auth/__init__.py
emeis/oidc_auth/authentication.py
emeis/oidc_auth/tests/__init__.py
emeis/oidc_auth/tests/test_authentication.py
emeis-2.2.4.data/data/emeis/core/templates/user_list.xlsx
emeis-2.2.4.dist-info/licenses/LICENSE
emeis-2.2.4.dist-info/METADATA
emeis-2.2.4.dist-info/WHEEL
emeis-2.2.4.dist-info/top_level.txt
emeis-2.2.4.dist-info/RECORD
