Metadata-Version: 2.4
Name: emeis
Version: 2.2.4
Summary: user management
Home-page: https://github.com/projectcaluma/emeis
Author: projectcaluma
License: License :: OSI Approved :: GNU General Public License v3 or later (GPLv3+)
Classifier: Development Status :: 4 - Beta
Classifier: Intended Audience :: Developers
Classifier: License :: OSI Approved :: GNU General Public License v3 or later (GPLv3+)
Classifier: Programming Language :: Python :: 3.11
License-File: LICENSE
Requires-Dist: django~=4.2
Requires-Dist: django-cors-headers<=4.7.0,>4.0.0
Requires-Dist: django-environ<=0.12,>=0.10
Requires-Dist: django-filter<26
Requires-Dist: django-generic-api-permissions~=1.0
Requires-Dist: django-localized-fields<7,>=6.4
Requires-Dist: django-postgres-extra<3
Requires-Dist: djangorestframework<4,>=3.12.4
Requires-Dist: djangorestframework-jsonapi~=8.0.0
Requires-Dist: gunicorn~=23.0.0
Requires-Dist: mozilla-django-oidc~=4.0
Requires-Dist: pyexcel<1,>0.6
Requires-Dist: pyexcel-xlsx<1,>=0.6.0
Requires-Dist: psycopg~=3.2
Requires-Dist: requests<3
Requires-Dist: openpyxl<4
Dynamic: author
Dynamic: classifier
Dynamic: description
Dynamic: description-content-type
Dynamic: home-page
Dynamic: license
Dynamic: license-file
Dynamic: requires-dist
Dynamic: summary
